{"pixen.kill":1,"stat.drop.minecraft.stone_pickaxe":3,"stat.chestOpened":5,"stat.useItem.minecraft.bow":1,"stat.entityKilledBy.seaserpent":1,"stat.pickup.minecraft.bone":81,"stat.craftItem.mujmajnkraftsbettersurvival.itemstonespear":56,"stat.pickup.lycanitesmobs.poisonraycharge":29,"aglebemu.kill":1,"stat.pickup.minecraft.gravel":44,"stat.leaveGame":1,"stat.pickup.minecraft.arrow":18,"stat.useItem.minecraft.log2":37,"stat.mineBlock.minecraft.cobblestone":3,"stat.pickup.minecraft.stone_pickaxe":21,"stat.pickup.minecraft.flint":9,"stat.pickup.minecraft.stone_axe":14,"stat.pickup.notreepunching.rock/andesite":2,"stat.pickup.minecraft.gold_nugget":16,"stat.pickup.minecraft.flower_pot":1,"geist.kill":1,"stat.useItem.notreepunching.rock/stone":4,"stat.craftItem.minecraft.iron_nugget":1,"stat.jump":1475,"stat.swimOneCm":7493,"zephyr.kill":2,"stat.pickup.minecraft.fence":12,"stat.pickup.minecraft.coal":61,"stat.fallOneCm":44087,"stat.climbOneCm":3674,"stat.useItem.minecraft.planks":17,"stat.pickup.minecraft.iron_ingot":4,"stat.pickup.scalinghealth.crystalshard":4,"stat.craftItem.realistictorches.glowstone_crystal":3,"stat.pickup.minecraft.glowstone_dust":30,"stat.drop.minecraft.stone_sword":4,"stat.useItem.minecraft.stone_axe":91,"stat.pickup.minecraft.gunpowder":26,"strider.kill":1,"stat.crouchOneCm":31773,"stat.pickup.iceandfire.pixie_dust":1,"stat.pickup.minecraft.spider_eye":26,"stat.craftItem.minecraft.iron_ingot":4,"stat.craftItem.minecraft.torch":12,"stat.useItem.spartanweaponry.boomerang_wood":29,"stat.pickup.minecraft.dirt":140,"stat.useItem.minecraft.dirt":10,"stat.pickup.lycanitesmobs.eechetikarm":3,"stat.pickup.minecraft.red_mushroom":27,"stat.useItem.minecraft.stone_slab2":13,"stat.pickup.minecraft.bow":1,"stat.craftingTableInteraction":31,"stat.pickup.minecraft.iron_ore":5,"stat.pickup.minecraft.rotten_flesh":114,"roc.kill":5,"stat.pickup.lycanitesmobs.poisongland":45,"jengu.kill":1,"reaper.kill":1,"stat.entityKilledBy.Spider":2,"warg.kill":2,"stat.pickup.quark.custom_chest":1,"stat.craftItem.minecraft.stone_axe":5,"stat.mineBlock.minecraft.log2":11,"stat.pickup.minecraft.leather":31,"stat.damageTaken":29169,"stat.pickup.minecraft.feather":18,"stat.pickup.notreepunching.rock/stone":731,"stat.pickup.lycanitesmobs.venomshotcharge":2,"stat.craftItem.minecraft.stone_pickaxe":7,"stat.mineBlock.minecraft.torch":15,"stat.pickup.minecraft.prismarine_shard":1,"gnekk.kill":1,"stat.pickup.minecraft.cobblestone":39,"stat.pickup.minecraft.log2":854,"stat.pickup.minecraft.dye":1,"stat.pickup.minecraft.planks":87,"stat.mineBlock.minecraft.clay":2,"stat.pickup.lycanitesmobs.aquapulsecharge":6,"stat.entityKilledBy.ZombieVillager":1,"eechetik.kill":5,"stat.craftItem.minecraft.stone_sword":4,"stat.flyOneCm":215000,"stat.pickup.minecraft.glass_bottle":1,"stat.entityKilledBy.firedragon":1,"stat.pickup.minecraft.wheat_seeds":7,"stat.pickup.minecraft.brown_mushroom":18,"stat.pickup.iceandfire.ash":1,"stat.pickup.minecraft.fish":7,"stat.entityKilledBy.Zombie":11,"stat.mineBlock.minecraft.gravel":27,"stat.useItem.minecraft.stone_pickaxe":196,"stat.useItem.minecraft.stone_sword":149,"stat.damageDealt":14223,"remobra.kill":1,"stat.mineBlock.minecraft.iron_ore":4,"stat.sleepInBed":16,"stat.timeSinceDeath":8059,"stat.mineBlock.minecraft.dirt":16,"stat.killEntity.VindicationIllager":3,"stat.pickup.minecraft.mutton":3,"stat.drop.minecraft.stick":1,"eyewig.kill":4,"stat.pickup.minecraft.double_plant":8,"stat.pickup.dynamictrees.darkoakseed":7,"stat.walkOneCm":970436,"stat.useItem.minecraft.torch":3,"lurker.kill":2,"stat.useItem.quark.custom_chest":1,"stat.pickup.minecraft.stick":373,"stat.craftItem.quark.custom_chest":4,"stat.pickup.minecraft.clay_ball":27,"stat.useItem.minecraft.cobblestone":3,"stat.furnaceInteraction":5,"stat.craftItem.minecraft.crafting_table":1,"stat.useItem.minecraft.gravel":2,"krake.kill":3,"stat.pickup.minecraft.iron_shovel":3,"stat.mineBlock.minecraft.double_plant":3,"stat.pickup.minecraft.carpet":1,"stat.killEntity.ZombieVillager":3,"stat.mineBlock.minecraft.coal_ore":15,"stat.killEntity.Creeper":1,"stat.talkedToVillager":4,"necrovore.kill":1,"ettin.kill":2,"stat.pickup.mujmajnkraftsbettersurvival.itemstonespear":103,"stat.pickup.minecraft.string":50,"stat.pickup.minecraft.log":12,"stat.pickup.minecraft.iron_pickaxe":1,"stat.craftItem.spartanweaponry.boomerang_wood":1,"stat.entityKilledBy.Skeleton":7,"stat.pickup.lycanitesmobs.spectralboltcharge":7,"stat.craftItem.minecraft.stone_slab2":0,"stat.pickup.minecraft.hay_block":16,"stat.pickup.lycanitesmobs.raw_arisaur_meat":2,"stat.mineBlock.minecraft.wool":50,"stat.pickup.minecraft.chicken":6,"stat.killEntity.Squid":1,"stat.sprintOneCm":685057,"stat.useItem.minecraft.fence":2,"stat.killEntity.Skeleton":7,"stat.pickup.roughtweaks.salve":1,"stat.killEntity.familiarfauna.butterfly":1,"stat.mineBlock.minecraft.fence":4,"stat.killEntity.Spider":4,"stat.entityKilledBy.VindicationIllager":16,"stat.pickup.minecraft.stone_sword":24,"stat.waystones:waystonesActivated":1,"stat.pickup.foodexpansion.itemsquid":12,"stat.pickup.bountifulbaubles.trinketmagiclenses":1,"stat.pickup.lycanitesmobs.tricksterflarecharge":7,"stat.pickup.minecraft.emerald":10,"stat.mobKills":78,"stat.pickup.lycanitesmobs.raw_krake_meat":8,"stat.pickup.minecraft.quartz":79,"ghoul.kill":4,"stat.entityKilledBy.Creeper":1,"stat.deaths":102,"stat.mineBlock.minecraft.planks":2,"stat.pickup.lycanitesmobs.geistliver":2,"stat.drop":11,"stat.pickup.lycanitesmobs.cleansingcrystal":6,"stat.pickup.potionfingers.ring":2,"stat.playOneMinute":210762,"stat.pickup.minecraft.torch":58,"stat.pickup.minecraft.red_flower":3,"stat.sneakTime":6090,"stat.useItem.lycanitesmobs.geistliver":1,"stat.pickup.minecraft.slime_ball":8,"stat.pickup.minecraft.wool":352,"stat.useItem.mujmajnkraftsbettersurvival.itemstonespear":90,"ent.kill":1,"stat.drop.minecraft.stone_axe":3,"stat.killEntity.Zombie":19,"stat.mineBlock.minecraft.hay_block":4,"stat.pickup.minecraft.yellow_flower":2,"stat.craftItem.minecraft.cobblestone":75,"stat.mineBlock.minecraft.stone":102,"stat.mineBlock.minecraft.tallgrass":24,"stat.diveOneCm":12301}